belso/__init__.py
belso/version.py
belso/core/__init__.py
belso/core/field.py
belso/core/processor.py
belso/core/schema.py
belso/providers/__init__.py
belso/providers/anthropic.py
belso/providers/google.py
belso/providers/huggingface.py
belso/providers/langchain.py
belso/providers/mistral.py
belso/providers/ollama.py
belso/providers/openai.py
belso/providers/base/__init__.py
belso/providers/base/json_schema.py
belso/providers/base/pydantic_model.py
belso/serialization/__init__.py
belso/serialization/json_format.py
belso/serialization/xml_format.py
belso/serialization/yaml_format.py
belso/tools/__init__.py
belso/tools/displaying.py
belso/tools/validating.py
belso/utils/__init__.py
belso/utils/detecting.py
belso/utils/formats.py
belso/utils/helpers.py
belso/utils/logging.py
belso/utils/mappings/__init__.py
belso/utils/mappings/extra_mappings.py
belso/utils/mappings/field_mappings.py
belso/utils/mappings/type_mappings.py
belso-0.0.4.dist-info/licenses/AUTHORS
belso-0.0.4.dist-info/licenses/LICENSE
belso-0.0.4.dist-info/METADATA
belso-0.0.4.dist-info/WHEEL
belso-0.0.4.dist-info/top_level.txt
belso-0.0.4.dist-info/RECORD
