Metadata-Version: 2.4
Name: belso
Version: 0.0.4
Summary: Better LLMs Structured Outputs
Home-page: https://github.com/MikiTwenty/belso
Author: Michele Ventimiglia
Author-email: michele.ventimiglia01@gmail.com
License: MIT
Classifier: Development Status :: 4 - Beta
Classifier: Intended Audience :: Developers
Classifier: Operating System :: OS Independent
Classifier: Programming Language :: Python
Requires-Python: >=3.10
License-File: LICENSE
License-File: AUTHORS
Requires-Dist: beartype
Requires-Dist: colorama
Requires-Dist: google-generativeai>=0.8.5
Requires-Dist: google.ai.generativelanguage>=0.6.15
Requires-Dist: pydantic
Requires-Dist: pytest
Requires-Dist: pyyaml
Requires-Dist: rich
Dynamic: author
Dynamic: author-email
Dynamic: classifier
Dynamic: description
Dynamic: description-content-type
Dynamic: home-page
Dynamic: license
Dynamic: license-file
Dynamic: requires-dist
Dynamic: requires-python
Dynamic: summary
